particlefilter.cp36-win32.pyd
slam3d-0.2.0.dist-info/LICENSE
slam3d-0.2.0.dist-info/METADATA
slam3d-0.2.0.dist-info/WHEEL
slam3d-0.2.0.dist-info/top_level.txt
slam3d-0.2.0.dist-info/RECORD
