Metadata-Version: 2.1
Name: slam3d
Version: 0.2.0
Summary: Simultaneous localization and mapping (SLAM) tools in 3D
Home-page: https://github.com/WiseLabCMU/slam3d
Author: Wireless Sensing and Embedded Systems Lab, Carnegie Mellon University
Author-email: wiselabCMU@gmail.com
License: BSD-3-Clause
Project-URL: Bug Reports, https://github.com/WiseLabCMU/slam3d/issues
Project-URL: Source, https://github.com/WiseLabCMU/slam3d
Keywords: slam slam3d 3d particlefilter particle filter localize localization map mapping tool tools
Platform: any
Classifier: Development Status :: 4 - Beta
Classifier: Intended Audience :: Developers
Classifier: License :: OSI Approved :: BSD License
Classifier: Programming Language :: C
Classifier: Programming Language :: Cython
Classifier: Programming Language :: Python :: 3
Classifier: Programming Language :: Python :: 3 :: Only
Classifier: Topic :: Scientific/Engineering
Classifier: Topic :: Scientific/Engineering :: Information Analysis
Classifier: Topic :: Scientific/Engineering :: Mathematics
Requires-Python: >=3.6, <4
License-File: LICENSE
